{"nodes": [{"id": "c_users_rudso_onedrive_documentos_site_sonda_sondas_app_configuracoes_components_syncstatuspanel_tsx", "label": "SyncStatusPanel.tsx", "file_type": "code", "type": "FUNCTION", "source_file": "C:\\Users\\rudso\\OneDrive\\Documentos\\Site_sonda\\sondas\\app\\configuracoes\\components\\SyncStatusPanel.tsx", "source_location": "L1", "complexity": 1, "loc": 1}, {"id": "syncstatuspanel_formatwhen", "label": "formatWhen()", "file_type": "code", "type": "FUNCTION", "source_file": "C:\\Users\\rudso\\OneDrive\\Documentos\\Site_sonda\\sondas\\app\\configuracoes\\components\\SyncStatusPanel.tsx", "source_location": "L7", "complexity": 10, "loc": 9}, {"id": "syncstatuspanel_syncstatuspanel", "label": "SyncStatusPanel()", "file_type": "code", "type": "FUNCTION", "source_file": "C:\\Users\\rudso\\OneDrive\\Documentos\\Site_sonda\\sondas\\app\\configuracoes\\components\\SyncStatusPanel.tsx", "source_location": "L21", "complexity": 18, "loc": 64}], "edges": [{"source": "c_users_rudso_onedrive_documentos_site_sonda_sondas_app_configuracoes_components_syncstatuspanel_tsx", "target": "react", "relation": "imports_from", "confidence": "EXTRACTED", "source_file": "C:\\Users\\rudso\\OneDrive\\Documentos\\Site_sonda\\sondas\\app\\configuracoes\\components\\SyncStatusPanel.tsx", "source_location": "L3", "weight": 1.0}, {"source": "c_users_rudso_onedrive_documentos_site_sonda_sondas_app_configuracoes_components_syncstatuspanel_tsx", "target": "lucide_react", "relation": "imports_from", "confidence": "EXTRACTED", "source_file": "C:\\Users\\rudso\\OneDrive\\Documentos\\Site_sonda\\sondas\\app\\configuracoes\\components\\SyncStatusPanel.tsx", "source_location": "L4", "weight": 1.0}, {"source": "c_users_rudso_onedrive_documentos_site_sonda_sondas_app_configuracoes_components_syncstatuspanel_tsx", "target": "types", "relation": "imports_from", "confidence": "EXTRACTED", "source_file": "C:\\Users\\rudso\\OneDrive\\Documentos\\Site_sonda\\sondas\\app\\configuracoes\\components\\SyncStatusPanel.tsx", "source_location": "L5", "weight": 1.0}, {"source": "c_users_rudso_onedrive_documentos_site_sonda_sondas_app_configuracoes_components_syncstatuspanel_tsx", "target": "syncstatuspanel_formatwhen", "relation": "contains", "confidence": "EXTRACTED", "source_file": "C:\\Users\\rudso\\OneDrive\\Documentos\\Site_sonda\\sondas\\app\\configuracoes\\components\\SyncStatusPanel.tsx", "source_location": "L7", "weight": 1.0}, {"source": "c_users_rudso_onedrive_documentos_site_sonda_sondas_app_configuracoes_components_syncstatuspanel_tsx", "target": "syncstatuspanel_syncstatuspanel", "relation": "contains", "confidence": "EXTRACTED", "source_file": "C:\\Users\\rudso\\OneDrive\\Documentos\\Site_sonda\\sondas\\app\\configuracoes\\components\\SyncStatusPanel.tsx", "source_location": "L21", "weight": 1.0}], "raw_calls": [{"caller_nid": "syncstatuspanel_formatwhen", "callee": "now", "source_file": "C:\\Users\\rudso\\OneDrive\\Documentos\\Site_sonda\\sondas\\app\\configuracoes\\components\\SyncStatusPanel.tsx", "source_location": "L8"}, {"caller_nid": "syncstatuspanel_formatwhen", "callee": "floor", "source_file": "C:\\Users\\rudso\\OneDrive\\Documentos\\Site_sonda\\sondas\\app\\configuracoes\\components\\SyncStatusPanel.tsx", "source_location": "L9"}, {"caller_nid": "syncstatuspanel_formatwhen", "callee": "floor", "source_file": "C:\\Users\\rudso\\OneDrive\\Documentos\\Site_sonda\\sondas\\app\\configuracoes\\components\\SyncStatusPanel.tsx", "source_location": "L12"}, {"caller_nid": "syncstatuspanel_formatwhen", "callee": "toLocaleString", "source_file": "C:\\Users\\rudso\\OneDrive\\Documentos\\Site_sonda\\sondas\\app\\configuracoes\\components\\SyncStatusPanel.tsx", "source_location": "L14"}, {"caller_nid": "syncstatuspanel_syncstatuspanel", "callee": "useState", "source_file": "C:\\Users\\rudso\\OneDrive\\Documentos\\Site_sonda\\sondas\\app\\configuracoes\\components\\SyncStatusPanel.tsx", "source_location": "L22"}, {"caller_nid": "syncstatuspanel_syncstatuspanel", "callee": "useState", "source_file": "C:\\Users\\rudso\\OneDrive\\Documentos\\Site_sonda\\sondas\\app\\configuracoes\\components\\SyncStatusPanel.tsx", "source_location": "L23"}, {"caller_nid": "syncstatuspanel_syncstatuspanel", "callee": "useState", "source_file": "C:\\Users\\rudso\\OneDrive\\Documentos\\Site_sonda\\sondas\\app\\configuracoes\\components\\SyncStatusPanel.tsx", "source_location": "L24"}, {"caller_nid": "syncstatuspanel_syncstatuspanel", "callee": "useState", "source_file": "C:\\Users\\rudso\\OneDrive\\Documentos\\Site_sonda\\sondas\\app\\configuracoes\\components\\SyncStatusPanel.tsx", "source_location": "L25"}, {"caller_nid": "syncstatuspanel_syncstatuspanel", "callee": "useState", "source_file": "C:\\Users\\rudso\\OneDrive\\Documentos\\Site_sonda\\sondas\\app\\configuracoes\\components\\SyncStatusPanel.tsx", "source_location": "L26"}, {"caller_nid": "syncstatuspanel_syncstatuspanel", "callee": "useCallback", "source_file": "C:\\Users\\rudso\\OneDrive\\Documentos\\Site_sonda\\sondas\\app\\configuracoes\\components\\SyncStatusPanel.tsx", "source_location": "L28"}, {"caller_nid": "syncstatuspanel_syncstatuspanel", "callee": "useEffect", "source_file": "C:\\Users\\rudso\\OneDrive\\Documentos\\Site_sonda\\sondas\\app\\configuracoes\\components\\SyncStatusPanel.tsx", "source_location": "L43"}, {"caller_nid": "syncstatuspanel_syncstatuspanel", "callee": "useCallback", "source_file": "C:\\Users\\rudso\\OneDrive\\Documentos\\Site_sonda\\sondas\\app\\configuracoes\\components\\SyncStatusPanel.tsx", "source_location": "L45"}, {"caller_nid": "syncstatuspanel_syncstatuspanel", "callee": "reduce", "source_file": "C:\\Users\\rudso\\OneDrive\\Documentos\\Site_sonda\\sondas\\app\\configuracoes\\components\\SyncStatusPanel.tsx", "source_location": "L56"}, {"caller_nid": "syncstatuspanel_syncstatuspanel", "callee": "values", "source_file": "C:\\Users\\rudso\\OneDrive\\Documentos\\Site_sonda\\sondas\\app\\configuracoes\\components\\SyncStatusPanel.tsx", "source_location": "L56"}, {"caller_nid": "syncstatuspanel_syncstatuspanel", "callee": "fonte", "source_file": "C:\\Users\\rudso\\OneDrive\\Documentos\\Site_sonda\\sondas\\app\\configuracoes\\components\\SyncStatusPanel.tsx", "source_location": "L67"}]}