{"nodes": [{"id": "c_users_rudso_onedrive_documentos_site_sonda_sondas_app_lib_geo_ts", "label": "geo.ts", "file_type": "code", "type": "FUNCTION", "source_file": "C:\\Users\\rudso\\OneDrive\\Documentos\\Site_sonda\\sondas\\app\\lib\\geo.ts", "source_location": "L1", "complexity": 1, "loc": 1}, {"id": "geo_haversinekm", "label": "haversineKm()", "file_type": "code", "type": "FUNCTION", "source_file": "C:\\Users\\rudso\\OneDrive\\Documentos\\Site_sonda\\sondas\\app\\lib\\geo.ts", "source_location": "L5", "complexity": 20, "loc": 8}, {"id": "geo_bearingdeg", "label": "bearingDeg()", "file_type": "code", "type": "FUNCTION", "source_file": "C:\\Users\\rudso\\OneDrive\\Documentos\\Site_sonda\\sondas\\app\\lib\\geo.ts", "source_location": "L15", "complexity": 17, "loc": 8}, {"id": "geo_cardinals", "label": "CARDINALS", "file_type": "code", "type": "FUNCTION", "source_file": "C:\\Users\\rudso\\OneDrive\\Documentos\\Site_sonda\\sondas\\app\\lib\\geo.ts", "source_location": "L24", "complexity": 1, "loc": 1}, {"id": "geo_bearingtocardinal", "label": "bearingToCardinal()", "file_type": "code", "type": "FUNCTION", "source_file": "C:\\Users\\rudso\\OneDrive\\Documentos\\Site_sonda\\sondas\\app\\lib\\geo.ts", "source_location": "L26", "complexity": 3, "loc": 3}, {"id": "geo_formatdistance", "label": "formatDistance()", "file_type": "code", "type": "FUNCTION", "source_file": "C:\\Users\\rudso\\OneDrive\\Documentos\\Site_sonda\\sondas\\app\\lib\\geo.ts", "source_location": "L30", "complexity": 6, "loc": 5}], "edges": [{"source": "c_users_rudso_onedrive_documentos_site_sonda_sondas_app_lib_geo_ts", "target": "geo_haversinekm", "relation": "contains", "confidence": "EXTRACTED", "source_file": "C:\\Users\\rudso\\OneDrive\\Documentos\\Site_sonda\\sondas\\app\\lib\\geo.ts", "source_location": "L5", "weight": 1.0}, {"source": "c_users_rudso_onedrive_documentos_site_sonda_sondas_app_lib_geo_ts", "target": "geo_bearingdeg", "relation": "contains", "confidence": "EXTRACTED", "source_file": "C:\\Users\\rudso\\OneDrive\\Documentos\\Site_sonda\\sondas\\app\\lib\\geo.ts", "source_location": "L15", "weight": 1.0}, {"source": "c_users_rudso_onedrive_documentos_site_sonda_sondas_app_lib_geo_ts", "target": "geo_cardinals", "relation": "contains", "confidence": "EXTRACTED", "source_file": "C:\\Users\\rudso\\OneDrive\\Documentos\\Site_sonda\\sondas\\app\\lib\\geo.ts", "source_location": "L24", "weight": 1.0}, {"source": "c_users_rudso_onedrive_documentos_site_sonda_sondas_app_lib_geo_ts", "target": "geo_bearingtocardinal", "relation": "contains", "confidence": "EXTRACTED", "source_file": "C:\\Users\\rudso\\OneDrive\\Documentos\\Site_sonda\\sondas\\app\\lib\\geo.ts", "source_location": "L26", "weight": 1.0}, {"source": "c_users_rudso_onedrive_documentos_site_sonda_sondas_app_lib_geo_ts", "target": "geo_formatdistance", "relation": "contains", "confidence": "EXTRACTED", "source_file": "C:\\Users\\rudso\\OneDrive\\Documentos\\Site_sonda\\sondas\\app\\lib\\geo.ts", "source_location": "L30", "weight": 1.0}], "raw_calls": [{"caller_nid": "geo_haversinekm", "callee": "sin", "source_file": "C:\\Users\\rudso\\OneDrive\\Documentos\\Site_sonda\\sondas\\app\\lib\\geo.ts", "source_location": "L9"}, {"caller_nid": "geo_haversinekm", "callee": "cos", "source_file": "C:\\Users\\rudso\\OneDrive\\Documentos\\Site_sonda\\sondas\\app\\lib\\geo.ts", "source_location": "L10"}, {"caller_nid": "geo_haversinekm", "callee": "cos", "source_file": "C:\\Users\\rudso\\OneDrive\\Documentos\\Site_sonda\\sondas\\app\\lib\\geo.ts", "source_location": "L10"}, {"caller_nid": "geo_haversinekm", "callee": "sin", "source_file": "C:\\Users\\rudso\\OneDrive\\Documentos\\Site_sonda\\sondas\\app\\lib\\geo.ts", "source_location": "L10"}, {"caller_nid": "geo_haversinekm", "callee": "asin", "source_file": "C:\\Users\\rudso\\OneDrive\\Documentos\\Site_sonda\\sondas\\app\\lib\\geo.ts", "source_location": "L11"}, {"caller_nid": "geo_haversinekm", "callee": "sqrt", "source_file": "C:\\Users\\rudso\\OneDrive\\Documentos\\Site_sonda\\sondas\\app\\lib\\geo.ts", "source_location": "L11"}, {"caller_nid": "geo_bearingdeg", "callee": "sin", "source_file": "C:\\Users\\rudso\\OneDrive\\Documentos\\Site_sonda\\sondas\\app\\lib\\geo.ts", "source_location": "L19"}, {"caller_nid": "geo_bearingdeg", "callee": "cos", "source_file": "C:\\Users\\rudso\\OneDrive\\Documentos\\Site_sonda\\sondas\\app\\lib\\geo.ts", "source_location": "L19"}, {"caller_nid": "geo_bearingdeg", "callee": "cos", "source_file": "C:\\Users\\rudso\\OneDrive\\Documentos\\Site_sonda\\sondas\\app\\lib\\geo.ts", "source_location": "L20"}, {"caller_nid": "geo_bearingdeg", "callee": "sin", "source_file": "C:\\Users\\rudso\\OneDrive\\Documentos\\Site_sonda\\sondas\\app\\lib\\geo.ts", "source_location": "L20"}, {"caller_nid": "geo_bearingdeg", "callee": "sin", "source_file": "C:\\Users\\rudso\\OneDrive\\Documentos\\Site_sonda\\sondas\\app\\lib\\geo.ts", "source_location": "L20"}, {"caller_nid": "geo_bearingdeg", "callee": "cos", "source_file": "C:\\Users\\rudso\\OneDrive\\Documentos\\Site_sonda\\sondas\\app\\lib\\geo.ts", "source_location": "L20"}, {"caller_nid": "geo_bearingdeg", "callee": "cos", "source_file": "C:\\Users\\rudso\\OneDrive\\Documentos\\Site_sonda\\sondas\\app\\lib\\geo.ts", "source_location": "L20"}, {"caller_nid": "geo_bearingdeg", "callee": "atan2", "source_file": "C:\\Users\\rudso\\OneDrive\\Documentos\\Site_sonda\\sondas\\app\\lib\\geo.ts", "source_location": "L21"}, {"caller_nid": "geo_bearingtocardinal", "callee": "round", "source_file": "C:\\Users\\rudso\\OneDrive\\Documentos\\Site_sonda\\sondas\\app\\lib\\geo.ts", "source_location": "L27"}, {"caller_nid": "geo_formatdistance", "callee": "round", "source_file": "C:\\Users\\rudso\\OneDrive\\Documentos\\Site_sonda\\sondas\\app\\lib\\geo.ts", "source_location": "L31"}, {"caller_nid": "geo_formatdistance", "callee": "toFixed", "source_file": "C:\\Users\\rudso\\OneDrive\\Documentos\\Site_sonda\\sondas\\app\\lib\\geo.ts", "source_location": "L32"}, {"caller_nid": "geo_formatdistance", "callee": "round", "source_file": "C:\\Users\\rudso\\OneDrive\\Documentos\\Site_sonda\\sondas\\app\\lib\\geo.ts", "source_location": "L33"}]}